{
    "type":"origins:multiple",
    "hidden":false,
    "description":"Reach and attack speed",
    "badges": [

    ],
    "lvl_1":{
        "type":"origins:conditioned_attribute",
        "condition": {
            "type": "origins:resource",
            "compare_to": 1,
            "comparison": "==",
            "resource": "fencers:wager/chips/true_focus"
        },
        "modifiers":[
            {
                "attribute": "minecraft:player.entity_interaction_range",
                "name": "Entity Reach",
                "operation": "addition",
                "value": 0.17
            },
            {
                "attribute": "minecraft:player.block_interaction_range",
                "name": "Block Reach",
                "operation": "addition",
                "value": 0.33
            }
        ],
        "tick_rate": 20
    },

    "lvl_2":{
        "type":"origins:conditioned_attribute",
        "condition": {
            "type": "origins:resource",
            "compare_to": 2,
            "comparison": "==",
            "resource": "fencers:wager/chips/true_focus"
        },
        "modifiers":[
            {
                "attribute": "minecraft:player.entity_interaction_range",
                "name": "Entity Reach",
                "operation": "addition",
                "value": 0.5
            },
            {
                "attribute": "minecraft:player.block_interaction_range",
                "name": "Block Reach",
                "operation": "addition",
                "value": 1
            },
            {
                "attribute": "minecraft:generic.attack_speed",
                "name": "Attack speed",
                "operation": "multiply_total",
                "value": 1.05
            }
        ],
        "tick_rate": 20
        
    },
    "lvl_3":{
        "type":"origins:conditioned_attribute",
        "condition": {
            "type": "origins:resource",
            "compare_to": 3,
            "comparison": "==",
            "resource": "fencers:wager/chips/true_focus"
        },
        "modifiers":[
            {
                "attribute": "minecraft:player.entity_interaction_range",
                "name": "Entity Reach",
                "operation": "addition",
                "value": 0.67
            },
            {
                "attribute": "minecraft:player.block_interaction_range",
                "name": "Block Reach",
                "operation": "addition",
                "value": 1.33
            },
            {
                "attribute": "minecraft:generic.attack_speed",
                "name": "Attack speed",
                "operation": "multiply_total",
                "value": 1.1
            }
        ],
        "tick_rate": 20
    },
    "lvl_4":{
        "type":"origins:conditioned_attribute",
        "condition": {
            "type": "origins:resource",
            "compare_to": 4,
            "comparison": "==",
            "resource": "fencers:wager/chips/true_focus"
        },
        "modifiers":[
            {
                "attribute": "minecraft:player.entity_interaction_range",
                "name": "Entity Reach",
                "operation": "addition",
                "value": 0.83
            },
            {
                "attribute": "minecraft:player.block_interaction_range",
                "name": "Block Reach",
                "operation": "addition",
                "value": 1.67
            },
            {
                "attribute": "minecraft:generic.attack_speed",
                "name": "Attack speed",
                "operation": "multiply_total",
                "value": 1.15
            }
        ],
        "tick_rate": 20
    },
    "lvl_5":{
        "type":"origins:conditioned_attribute",
        "condition": {
            "type": "origins:resource",
            "compare_to": 5,
            "comparison": "==",
            "resource": "fencers:wager/chips/true_focus"
        },
        "modifiers":[
            {
                "attribute": "minecraft:player.entity_interaction_range",
                "name": "Entity Reach",
                "operation": "addition",
                "value": 1
            },
            {
                "attribute": "minecraft:player.block_interaction_range",
                "name": "Block Reach",
                "operation": "addition",
                "value": 2
            },
            {
                "attribute": "minecraft:generic.attack_speed",
                "name": "Attack speed",
                "operation": "multiply_total",
                "value": 1.2
            },
            {
                "attribute": "minecraft:player.sweeping_damage_ratio",
                "name": "Sweeping",
                "operation": "multiply_total",
                "value": 2
                
            }
        ],
        "tick_rate": 20
    }
}